flask_wiki/__init__.py
flask_wiki/api.py
flask_wiki/cli.py
flask_wiki/config.py
flask_wiki/forms.py
flask_wiki/markdown_ext.py
flask_wiki/static/css/font-awesome.css
flask_wiki/static/css/font-awesome.min.css
flask_wiki/static/css/wiki.css
flask_wiki/static/fonts/FontAwesome.otf
flask_wiki/static/fonts/fontawesome-webfont.eot
flask_wiki/static/fonts/fontawesome-webfont.svg
flask_wiki/static/fonts/fontawesome-webfont.ttf
flask_wiki/static/fonts/fontawesome-webfont.woff
flask_wiki/static/fonts/fontawesome-webfont.woff2
flask_wiki/static/js/wiki.js
flask_wiki/static/less/animated.less
flask_wiki/static/less/bordered-pulled.less
flask_wiki/static/less/core.less
flask_wiki/static/less/fixed-width.less
flask_wiki/static/less/font-awesome.less
flask_wiki/static/less/icons.less
flask_wiki/static/less/larger.less
flask_wiki/static/less/list.less
flask_wiki/static/less/mixins.less
flask_wiki/static/less/path.less
flask_wiki/static/less/rotated-flipped.less
flask_wiki/static/less/screen-reader.less
flask_wiki/static/less/stacked.less
flask_wiki/static/less/variables.less
flask_wiki/static/scss/_animated.scss
flask_wiki/static/scss/_bordered-pulled.scss
flask_wiki/static/scss/_core.scss
flask_wiki/static/scss/_fixed-width.scss
flask_wiki/static/scss/_icons.scss
flask_wiki/static/scss/_larger.scss
flask_wiki/static/scss/_list.scss
flask_wiki/static/scss/_mixins.scss
flask_wiki/static/scss/_path.scss
flask_wiki/static/scss/_rotated-flipped.scss
flask_wiki/static/scss/_screen-reader.scss
flask_wiki/static/scss/_stacked.scss
flask_wiki/static/scss/_variables.scss
flask_wiki/static/scss/font-awesome.scss
flask_wiki/templates/wiki/403.html
flask_wiki/templates/wiki/404.html
flask_wiki/templates/wiki/base.html
flask_wiki/templates/wiki/editor.html
flask_wiki/templates/wiki/files.html
flask_wiki/templates/wiki/navigation.html
flask_wiki/templates/wiki/page.html
flask_wiki/templates/wiki/search.html
flask_wiki/translations/de/LC_MESSAGES/messages.mo
flask_wiki-1.0.3.dist-info/licenses/LICENSE
flask_wiki-1.0.3.dist-info/WHEEL
flask_wiki-1.0.3.dist-info/entry_points.txt
flask_wiki-1.0.3.dist-info/METADATA
flask_wiki-1.0.3.dist-info/RECORD
