Metadata-Version: 2.4
Name: flask-wiki
Version: 1.0.3
Summary: Simple file-based wiki for Flask
Author: RERO+
Author-email: RERO+ <software@rero.ch>
License-Expression: BSD-3-Clause
License-File: LICENSE
Requires-Dist: bootstrap-flask
Requires-Dist: flask
Requires-Dist: flask-wtf
Requires-Dist: babel>=2.9.1
Requires-Dist: flask-babel>=3.0.0
Requires-Dist: wtforms
Requires-Dist: werkzeug>=0.15
Requires-Dist: jinja2>=3.0.0
Requires-Dist: markdown<3.4.0
Requires-Dist: py<2.0.0
Requires-Dist: beautifulsoup4<5.0.0
Requires-Dist: click<9.0.0
Requires-Dist: whoosh-reloaded>=2.7.5
Requires-Python: >=3.9.2, <3.13
